{
    "0": {
        "name": "Article Example",
        "description": "Article Description Example",
        "date": "Passed MILTIME CDT Month Day Year",
        "amendments": 0
    },
    "1": {
        "name": "Article 1",
        "description": "New Caledonia is a pretty freaking cool place.",
        "date": "Passed 2203 CDT May 23 2020",
        "amendments": 0
    },
    "2": {
        "name": "Article 2",
        "description": "Everybodys got rights.",
        "date": "Passed 2203 CDT May 23 2020",
        "amendments": 0
    },
    "3": {
        "name": "Article 3",
        "description": "Don’t kill people, that's not nice. Don’t rob people, that's not nice. Don’t trespass, that's not nice.",
        "date": "Passed 2203 CDT May 23 2020",
        "amendments": 0
    },
    "4": {
        "name": "Article 4",
        "description": "Mines are public property",
        "date": "Passed 2211 CDT May 23 2020",
        "amendments": 0
    },
    "5": {
        "name": "Article 5",
        "description": "The Music Bot has to be at 5% volume or less at all times",
        "date": "Passed 2136 CDT May 26 2020",
        "amendments": 1
    },
    "5.1": {
        "name": "Article 5 - Amendment 1",
        "description": "Those who kill eardrums without consent receive a minimum of 2 days in prison.",
        "date": "Passed 2141 CDT May 26 2020",
        "amendments": 0
    },
    "6": {
        "name": "Article 6",
        "description": "Yelling, constantly talking too much, or repeating the same thing over and over again is not permitted if so you will be banned from the chat.",
        "date": "Passed 2136 CDT May 30 2020",
        "amendments": 0
    },
    "7": {
        "name": "Article 7",
        "description": "The Enforcers and The Enforcer Captain must follow the [Enforcer Code of Conduct](https://docs.google.com/document/d/1ntRTmBb5t_9-FpVyBRJvn4sJ3rOcMUbseCPgQG1vi6E/edit?usp=sharing).",
        "date": "Passed 2243 CDT June 1 2020",
        "amendments": 0
    },
    "8": {
        "name": "Article 8",
        "description": "No cruel and unusual punishment will be enacted. If exile is necessary, it will be for a maximum of 7 Minecraft days. Any additional sentences will be gradually added as seen fit by the government. Under no circumstances will the accused be kicked from the game. That's not cool.",
        "date": "Passed 0953 CDT June 2 2020",
        "amendments": 1
    },
    "8.1": {
        "name": "Article 8 - Amendment 1",
        "description": "A long term and/or indefinite ban can be enacted if the entire innocent Council deems it necessary.",
        "date": "Passed 2004 CDT August 8 2020",
        "amendments": 0
    },
    "9": {
        "name": "Article 9",
        "description": "Gambling is legalized, and will follow Vegas rules (i.e. You cheat, you die).",
        "date": "Passed 0953 CDT June 2 2020",
        "amendments": 0
    },
    "10": {
        "name": "Article 10",
        "description": "Villagers of New Llanfairpwllgwyngyllgogerychwyrndrobwllllantysiliogogogoch hold the same status as any autonomous citizen of New Caledonia.",
        "date": "Passed 2155 CDT June 5 2020",
        "amendments": 0
    },
    "11": {
        "name": "Article 11",
        "description": "Arrests may not be predated. Therefore, all crimes committed before the date of the law's signing are legal.",
        "date": "Passed 2155 CDT June 5 2020",
        "amendments": 0
    },
    "12": {
        "name": "Article 12",
        "description": "NO SWEARING ON MY CHRISTIAN MINECRAFT SERVER",
        "date": "Passed 2229 CDT June 13 2020",
        "amendments": 0
    },
    "13": {
        "name": "Article 13",
        "description": "for those who didn't know who the Clan Elders works, it like this:\nAlex - President - Sign laws\nAlan - Vice President (Congress) - Comes up with new laws and projects\nConnor - Judge - Enforces laws through the Enforcers and resolves any other law problems (court trials)",
        "date": "Passed 1220 CDT June 16 2020",
        "amendments": 0
    },
    "14": {
        "name": "Article 14",
        "description": "Prepared foods cannot be sold by businesses that have not determined themselves as some sort of eatery.",
        "date": "Passed 0020 CDT June 16 2020",
        "amendments": 1
    },
    "14.1": {
        "name": "Article 14 - Amendment 1 (physical location act)",
        "description": "No New Caledonia (nation) business may not sell products without a physical location. The location must be a professional, non-temporary building in 10X10 space. Any business in defying this law will have to close down until found in compliance with this law.",
        "date": "Passed 2304 CDT September 11 2020",
        "amendments": 0
    },
    "15": {
        "name": "Article 15 - REPEALED (15:1)",
        "description": "Formula for property tax: Perimeter + Number of Floors ÷ 6 then round it up",
        "date": "Passed 1217 CDT June 17 2020",
        "amendments": 0
    },
    "16": {
        "name": "Article 16",
        "description": "On the New Caledonia server, it is prohibited to be on the server before 7:50 PM or after 10 PM. This applies to all except the President and those given express Council/President permission. Those caught disobeying this law will be punished for robbery.",
        "date": "Passed 1300 CDT June 17 2020",
        "amendments": 0
    },
    "17": {
        "name": "Article 17",
        "description": "The sole ruling power in New Caledonia will be the Council of Elders. It is a triumvirate. Each position is elected by the family and those others adopted. The seat is voted for every 4 months. However at any time during the term, any member of the family may challenge that family's representative to an arena fight. This Council will have the power to suggest, vote on, and enforce laws through government Enforcers. They will also have the power, as a jury, to acquit or convict any accused persons given probable cause for arrest and accusation. Citizens cannot be both Enforcer and Councilman. They must give up an Enforcer role to take a Council seat. The Council will subsequently find a replacement Enforcer. This will go into effect following the current governmental investigation. If a similar investigation were to take place, anyone involved will be removed from the Council temporarily. In their absence, they will appoint a temporary replacement.",
        "date": "Passed 2242 CDT June 21 2020",
        "amendments": 4
    },
    "17.1": {
        "name": "Article 17 - Amendment 1",
        "description": "Instead of families, each Councilman will represent a borough. Each of the three boroughs in the City of New Caledonia will get representation in the National Council. Also, SMAC challenges will be replaced by approval polls, which will be opened for four days. If the questioned has his rating fall below 50%, an election will take place, in which the deadline for registering and the election itself are exactly 14 days after the poll closes. Official alignment will be set by the sitting Council as of the passage of this amendment.\n\nTwin Peaks (On the hill): Alan, Nate, Aidan\nNew Caledonia (East of Hwy 17): Alex, Eddie, Ethan\nNew Vegas (West of Hwy 17): Connor, Daniel, Joey",
        "date": "Passed 2055 CDT October 8 2020",
        "amendments": 0
    },
    "17.2": {
        "name": "Article 17 - Amendment 2",
        "description": "On Approval Polls. Approval polls of a Councilman may be proposed by someone within the same borough. They may only be proposed at a certain rate: 2 weeks after the term starts, and there must be 1 month between each attempt. A less than 50% rate can cause another election in the borough. The sitting Councilman, even if not approved of, may run in this new election. The approval poll will be open for 72 hours, or until all citizens have voted. The poll will be run by the Speaker, who is the Councilman with the most Council experience. In the event that the Speaker is the one included on the poll, an unrelated Councilman will run the poll with him.",
        "date": "Passed 2120 CDT October 21 2020",
        "amendments": 0
    },
    "17.3": {
        "name": "Article 17 - Amendment 3",
        "description": "As of March 24, 2021 (CDT), the names of the three boroughs are: Crestview (represented by Alex Snyder), New Vegas (rep. Connor McClintic), and Twin Peaks (rep. Alan Saucer).",
        "date": "Passed 2145 CDT March 23 2021",
        "amendments": 0
    },
    "17.4": {
        "name": "Article 17 - Amendment 4",
        "description": "Impeachment proceedings, when requested, must be promptly started. When they are started, the approval poll must be open for one week, and if an emergency election is required, that too must be open for one week immediately after the poll's closing.",
        "date": "Passed 1835 CDT May 26 2021",
        "amendments": 0
    },
    "18": {
        "name": "Article 18 - REPLACED (18:1)",
        "description": "IF THE ACTIVITY ON THIS MINECRAFT SERVER CONTINUES TO SPARK ARGUMENTS, FIGHTING, AND NEGATIVE BEHAVIOR IN OUR HOME I WILL ME FORCE TERMINATED THE SERVER BY PARENTS. EVERYONE NEEDS TO PLAY NICE OR NOT PLAY - ALAN, EDDIE, JOEY'S PARENTS",
        "date": "Passed 2205 CDT June 26 2020",
        "amendments": 1
    },
    "18.1": {
        "name": "Article 18 - Amendment 1",
        "description": "The previous wording of this article is now void, and is hailed as an announcement. The repeated offense of bullying and harassment is now illegal. These are defined as repeated attempts to insult one person. This is punishable by a temporary ban and will be determined by a court.",
        "date": "Passed 1242 CDT July 13 2020",
        "amendments": 0
    },
    "19": {
        "name": "Article 19",
        "description": "Treason, as one of the understood laws, needs an official definition. \"Treason\" is hereby defined as any act taken against the government or an official.",
        "date": "Passed 1209 CDT July 13 2020",
        "amendments": 0
    },
    "20": {
        "name": "Article 20 (Parental Act)",
        "description": "No parental legislature is allowed from here out without Council approval.",
        "date": "Passed 2110 CDT July 13 2020",
        "amendments": 1
    },
    "20.1": {
        "name": "Article 20 - Amendment 1",
        "description": "Any and all parental action, including but not limited to, banning citizens and destroying New Caledonia, is hereby prohibited. Any legal action must be presented by a Councilman.",
        "date": "Passed 0904 AM CDT July 28 2020",
        "amendments": 0
    },
    "21": {
        "name": "Article 21",
        "description": "If a citizen gets worked up, and begins to use petty arguments and angrily yells over the voice chat, they will be removed for 15 minutes. Failure to observe this law will result in a trial, and is punishable by up to five days in prison.",
        "date": "Passed 2110 AM CDT July 13 2020",
        "amendments": 0
    },
    "22": {
        "name": "Article 22 (Command Block Act)",
        "description": "No command blocks that are no approved by the council. EXAMPLES: Gamemode changers, Hard items summons, a timer that teleports you home in 5 mins",
        "date": "Passed 10:25 PM July 18 CDT 2020",
        "amendments": 0
    },
    "23": {
        "name": "Article 23",
        "description": "Those who have been given Creative privileges are prohibited from sharing Creative sourced items with those who have not. This is punishable by a revoking of Creative privileges and may result in a loss of office.",
        "date": "Passed 1016 PM CDT July 20 2020",
        "amendments": 1
    },
    "23.1": {
        "name": "Article 23 - Amendment 1",
        "description": "In order to encourage use of the national economy, a cycle of legalized Creative usage will be implemented. On January 15th and July 15th, there will be periods of 3 months in which Creative privileges are revoked. Outside of these limited periods, Councilmen, National Enforcers, and Governors will be given Operator privileges, and any projects under NCCA and NCTA will be allowed with Creative privileges.",
        "date": "Passed 0047 CDT April 12 2021",
        "amendments": 0
    },
    "24": {
        "name": "Article 24",
        "description": "Pardon of any crime may be given by way of a unanimous vote of the Council. Any record of the crime pardoned shall be wiped clean.",
        "date": "Passed 2053 CDT July 28 2020",
        "amendments": 0
    },
    "25": {
        "name": "Article 25",
        "description": "Should any arrests be made and the accused is either acquitted or their trial canceled, the Council will pay reparation of 30 Emeralds to that person. The settlement of a case does not apply.",
        "date": "Passed 1728 PM CDT July 30 2020",
        "amendments": 0
    },
    "26": {
        "name": "Article 26",
        "description": "Any building commissioned by the NCCA is open to event hosts. However, in order to add a person or company name to the event or pay participants, it must be approved by a majority of Councilmen.",
        "date": "Passed 1227 CDT August 8 2020",
        "amendments": 0
    },
    "27": {
        "name": "Article 27",
        "description": "Voter fraud is punishable by either a 30 Emerald fine or 3 days in jail.",
        "date": "Passed 1538 CDT August 10 2020",
        "amendments": 1
    },
    "27.1": {
        "name": "Article 27 - Amendment 1",
        "description": "Voter fraud is punishable by a 10 Credit fine, due within a week unless probation is enforced. Each citizen has the right to non-disclosure regarding his vote, unless questioning is necessary for determining voter fraud.",
        "date": "Passed 2114 CDT October 12 2020",
        "amendments": 0
    },
    "28": {
        "name": "Article 28",
        "description": "Harassment in direct messages is still punishable under New Caledonia laws.",
        "date": "Passed 1540 CDT August 10 2020",
        "amendments": 0
    },
    "29": {
        "name": "Article 29 (Common Sense Act)",
        "description": "The following is illegal: TNT (except for mining), lobbying, perjury, government censorship without due cause, voter fraud, election tampering, commanding Enforcers not as a Councilman, tax evasion, unapproved government reimbursement, and dishonoring of a ban and/or jail time. Furthermore, any court evasion will be an assumed loss, repeat offenders shall have a graduated punishment culminating in an indefinite ban, and the Court's ruling is final, and holds judicial review. The "annoyance crimes", which include spamming, bullying, and harassment, do not require a trial.",
        "date": "Passed 750 PM CDT, August 14 2020",
        "amendments": 5
    },
    "29.1": {
        "name": "Article 29 - Amendment 1",
        "description": "A company and its owner are one and the same legally. When one sues a company, the owner is responsible for unpaid charges. If still unpaid, the ban will fall on the owner, as is normal. In other words, the owner is the company in a legal sense.",
        "date": "Passed 1726 CDT October 6 2020",
        "amendments": 0
    },
    "29.2": {
        "name": "Article 29 - Amendment 2 (Privacy Act)",
        "description": "The following is illegal: trespassing, or the act of entering someone's private property without permission, and flying over does not apply; and searching without a warrant issued by majority innocent Council. Furthermore, the right of the people to hold private calls and/or dealings shall not be infringed, unless said dealing is illegal by other laws.",
        "date": "Passed 0004 CDT October 11 2020",
        "amendments": 0
    },
    "29.3": {
        "name": "Article 29 - Amendment 3",
        "description": "Distribution (i.e. selling and sharing) of any illegal-to-use items is hereby prohibited, nor can they set the usage when selling. Distributors of otherwise legal items used illegally (i.e. certain potions) are released from liability in a court of law.",
        "date": "Passed 1800 CDT November 7 2020",
        "amendments": 0
    },
    "29.4": {
        "name": "Article 29 - Amendment 4",
        "description": "A citizen may not be tried twice for the same crime regardless of what evidence may have presented itself after the first trial. In essence, double jeopardy in the sense of justice is prohibited.",
        "date": "Passed 0011 CST November 21 2020",
        "amendments": 0
    },
    "29.5": {
        "name": "Article 29 - Amendment 5",
        "description": "The use and/or distribution of any Potions of Invisibility is hereby prohibited. Each use must be approved by a majority innocent Council, if applicable. Violators will be prosecuted.",
        "date": "Passed 1813 CST December 2 2020",
        "amendments": 0
    },
    "30": {
        "name": "Article 30 (School Act)",
        "description": "During the school year, with notable exceptions given by the Council, no person shall be on New Caledonia's Minecraft until school/homework is done, including any parameters set by the parent of the affected (including chores). School and lunch breaks are allowed. No one is allowed to enter the Minecraft server after one's given a curfew. Curfew given by New Caledonia will be in two groups: Elders: Alex, Connor, Diego, Nate, Alan, and anyone else who is decided by the council. Alpha: Eddie, Joey, Daniel, Ethan, Aiden, Sal, and anyone else who is decided by the council. Elder curfew is 23:00 their time zone. Alpha curfew is 22:30 their time zone. In order to enforce this properly, when a time zone changes, it must be reported. This article may be temporarily revoked for certain breaks (i.e. Winter, Spring, Fall break).",
        "date": "Passed 1813 CST December 2 2020",
        "amendments": 0
    },
    "31": {
        "name": "Article 31 (Tax Act)",
        "description": "Effective immediately, taxes are to be collected every other Saturday, unless otherwise notified. Tax evasion is a serious offense and will be dealt with as such.",
        "date": "Passed 654 AM CDT August 26 2020",
        "amendments": 1
    },
    "31.1": {
        "name": "Article 31 - Amendment 1 (Citizenship Tax)",
        "description": "Property taxes are hereby eliminated. Instead, a $5 Citizenship Tax will be collected each month on the 15th.",
        "date": "Passed 1949 CDT September 6 2020",
        "amendments": 1
    },
    "32": {
        "name": "Article 32",
        "description": "Raids can be started legally, but preparedness is required. If any damage should occur, the instigator shall be held responsible (i.e. damage to public property)",
        "date": "Passed 1409 CDT August 30 2020",
        "amendments": 0
    },
    "33": {
        "name": "Article 33",
        "description": "Only Councilmen, and those employed by NCTA or NCCA, may be given Creative privileges. This is for the purpose of reducing cheating and should be used with any previous Creative related laws.",
        "date": "Passed 1217 CDT September 6 2020",
        "amendments": 0
    },
    "34": {
        "name": "Article 34 (Economy Act)",
        "description": "Effective on September 12, 2020, the Credit is the new currency and standard of the New Caledonian economy. Each citizen will be given 64 Credits, and also may trade in 128 Emeralds for 1 Credit until an undisclosed date and time. Taxes have been reset accordingly, as set in Article 31 Amendment 1 and/or later. Furthermore, Article 34 establishes the Bank of New Caledonia (BONC). Checks may be used, but BONC must be notified so as to move funds accordingly.",
        "date": "Passed 2025 CDT September 6 2020",
        "amendments": 1
    },
    "34.1": {
        "name": "Article 34 Amendment 1",
        "description": "Instead of 64 Credits, each citizen will be issued 128 Credits on September 12. This does not affect the value or trading of Emeralds.",
        "date": "Passed 2326 CDT September 10 2020",
        "amendments": 0
    }
}
